nlb/sharetrace/interface.py
nlb/sharetrace/sharetrace
nlb/sharetrace/sharetrace.py
nlb/sharetrace/sharetrace.venv.pth
nlb/sharetrace/sharetrace_demo
nlb/sharetrace/sharetrace_demo.py
nlb/sharetrace/sharetrace_demo.venv.pth
nlb/sharetrace/st.py
nlb/util/click_utils.py
nlb/util/console_utils.py
nlb_legacy-0.7.1.dist-info/WHEEL
nlb_legacy-0.7.1.dist-info/METADATA
nlb_legacy-0.7.1.dist-info/entry_points.txt
nlb_legacy-0.7.1.data/data/share/completions/sharetrace-completion.bash
nlb_legacy-0.7.1.data/data/share/completions/sharetrace_demo-completion.bash
nlb_legacy-0.7.1.data/data/share/completions/venv_completions-completion.bash
nlb_legacy-0.7.1.dist-info/RECORD
