Metadata-Version: 2.1
Name: nlb_legacy
License: MIT
Summary: Ryan's fever dreams
Project-URL: Issues, https://github.com/RyanDraves/nlb/issues
Project-URL: Repository, https://github.com/RyanDraves/nlb
Requires-Python: >=3.10
Requires-Dist: jinja2<4,>=3.1.0
Requires-Dist: marshmallow-dataclass<9,>=8.7.1
Requires-Dist: pygments<3,>=2.16.0
Requires-Dist: rich<14,>=13.9.4
Requires-Dist: rich-click<2,>=1.8.3
Version: 0.7.1
